barbari/__init__.py
barbari/config.py
barbari/constants.py
barbari/exceptions.py
barbari/flatcam.py
barbari/gerbers.py
barbari/main.py
barbari/commands/__init__.py
barbari/commands/build.py
barbari/commands/build_script.py
barbari/commands/display_config.py
barbari/commands/generate_config.py
barbari/commands/list_configs.py
barbari/commands/setup_flatcam.py
barbari/configs/coddingtonbear.yaml
barbari/configs/copper_wire_vias.yaml
barbari/configs/default_alignment_holes.yaml
barbari/configs/default_edge_cuts.yaml
barbari/configs/default_isolation_routing.yaml
barbari/configs/drilled_04_10.yaml
barbari/configs/drilled_pth_04_11.yaml
barbari/configs/example.yaml
barbari/configs/milled_10.yaml
barbari/configs/milled_11.yaml
barbari/configs/rivets.yaml
barbari/configs/simple.yaml
barbari/configs/slots_10.yaml
barbari-3.0.3.dist-info/METADATA
barbari-3.0.3.dist-info/WHEEL
barbari-3.0.3.dist-info/entry_points.txt
barbari-3.0.3.dist-info/top_level.txt
barbari-3.0.3.dist-info/RECORD
