Metadata-Version: 2.1
Name: barbari
Version: 3.0.3
Summary: Automates Flatcam generation of G-code for my (and maybe your) PCB milling process.
Home-page: https://github.com/coddingtonbear/barbari
Author: Adam Coddington
Author-email: me@adamcoddington.net
Classifier: License :: OSI Approved :: MIT License
Classifier: Operating System :: OS Independent
Classifier: Programming Language :: Python :: 3
Requires-Dist: appdirs (<2,>=1.4.3)
Requires-Dist: pcb-tools (<1,>=0.1.6)
Requires-Dist: pyyaml (<6,>=5.4.1)
Requires-Dist: rich (<13,>=12)
